naja_atra_jinja/__init__.py
naja_atra_jinja-1.0.2.dist-info/LICENSE
naja_atra_jinja-1.0.2.dist-info/METADATA
naja_atra_jinja-1.0.2.dist-info/WHEEL
naja_atra_jinja-1.0.2.dist-info/top_level.txt
naja_atra_jinja-1.0.2.dist-info/RECORD
