Metadata-Version: 2.1
Name: naja-atra-jinja
Version: 1.0.2
Summary: This is a simple http server, use MVC like design.
Author-email: keijack <keijack.wu@gmail.com>
License: MIT License
Project-URL: homepage, https://github.com/naja-atra/naja-atra-jinja
Project-URL: repository, https://github.com/naja-atra/naja-atra-jinja
Keywords: http-server,jinja,http,web,web-server
Classifier: Programming Language :: Python :: 3
Classifier: License :: OSI Approved :: MIT License
Classifier: Operating System :: OS Independent
Requires-Python: >=3.7
License-File: LICENSE
Requires-Dist: naja-atra
Requires-Dist: jinja2 >=3.1
